{
    "user": {
        "id": "7072011091736593413",
        "shortId": "",
        "uniqueId": "pashakiller882",
        "nickname": "\u041f\u0430\u0448\u0430 \u042f\u043d\u043a\u043e\u0432\u0435\u0446\u044c",
        "avatarLarger": "https://p16-sign-va.tiktokcdn.com/tos-maliva-avt-0068/c3bdbc45ae51929c2aa2dc5c03e09d1a~c5_1080x1080.jpeg?x-expires=1647986400&x-signature=%2BLSrUUj3fZFp0LW4f2KFyJ4%2FGuA%3D",
        "avatarMedium": "https://p16-sign-va.tiktokcdn.com/tos-maliva-avt-0068/c3bdbc45ae51929c2aa2dc5c03e09d1a~c5_720x720.jpeg?x-expires=1647986400&x-signature=EAfzURu8OsRBbMJ%2FjbSD2iUexJI%3D",
        "avatarThumb": "https://p16-sign-va.tiktokcdn.com/tos-maliva-avt-0068/c3bdbc45ae51929c2aa2dc5c03e09d1a~c5_100x100.jpeg?x-expires=1647986400&x-signature=qwJlyjXoIvkTlnZ57dsX1WNXjBc%3D",
        "signature": "",
        "createTime": 1647421122,
        "verified": false,
        "secUid": "MS4wLjABAAAANRY6SpQtt5g6USQ_6Mw_DLEg2ANp57Wh-1WPlTnN0ekWgyX2_b-wxygxRrGx4aR_",
        "ftc": false,
        "relation": 0,
        "openFavorite": false,
        "commentSetting": 0,
        "duetSetting": 0,
        "stitchSetting": 0,
        "privateAccount": false,
        "secret": false,
        "isADVirtual": false,
        "roomId": ""
    },
    "stats": {
        "followerCount": 78,
        "followingCount": 132,
        "heart": 610,
        "heartCount": 610,
        "videoCount": 24,
        "diggCount": 0
    },
    "itemList": []
}