{
    "user": {
        "id": "7083464359359398917",
        "shortId": "",
        "uniqueId": "ukraine.superlove",
        "nickname": "\u0417\u0430 \u0423\u043a\u0440\u0430\u0457\u043d\u0443 !!!",
        "avatarLarger": "https://p16-sign-va.tiktokcdn.com/tos-maliva-avt-0068/2dffd2a1f3921be9a82b31e1c9de083b~c5_1080x1080.jpeg?x-expires=1649638800&x-signature=e3PrenyNSZrL3N0jf%2F3aHQyefvU%3D",
        "avatarMedium": "https://p16-sign-va.tiktokcdn.com/tos-maliva-avt-0068/2dffd2a1f3921be9a82b31e1c9de083b~c5_720x720.jpeg?x-expires=1649638800&x-signature=o80fQaF3Cj9nNVv4YYj33QbfZJ0%3D",
        "avatarThumb": "https://p16-sign-va.tiktokcdn.com/tos-maliva-avt-0068/2dffd2a1f3921be9a82b31e1c9de083b~c5_100x100.jpeg?x-expires=1649638800&x-signature=cnV9UaOW7QbB5co2mGiCimQ28ng%3D",
        "signature": "\u041c\u0438 \u043f\u043e\u0432\u0438\u043d\u043d\u0456 \u043e\u0431\u0456\u0439\u0442\u0438 \u0440\u043e\u0441\u0441\u0438\u044f\u043d \ud83d\ude0e",
        "createTime": 1649247621,
        "verified": false,
        "secUid": "MS4wLjABAAAA7pxQ6qwk6iqAvDjFiPqiSrjF06ANvkDv3OuhJaig7rP5ghwV49mLaLffp_w5ZhXi",
        "ftc": false,
        "relation": 0,
        "openFavorite": false,
        "commentSetting": 0,
        "duetSetting": 0,
        "stitchSetting": 0,
        "privateAccount": false,
        "secret": false,
        "isADVirtual": false,
        "roomId": ""
    },
    "stats": {
        "followerCount": 757,
        "followingCount": 10,
        "heart": 918,
        "heartCount": 918,
        "videoCount": 50,
        "diggCount": 0
    },
    "itemList": []
}