{
    "user": {
        "id": "7071411136591840262",
        "shortId": "",
        "uniqueId": "corrupireland",
        "nickname": "corrupireland",
        "avatarLarger": "https://p16-sign-va.tiktokcdn.com/tos-maliva-avt-0068/31672b0fc5b2724e2dec56d7be0edc68~c5_1080x1080.jpeg?x-expires=1650934800&x-signature=0ED1f6p%2FVsDoiPhjjlIk12JVYbk%3D",
        "avatarMedium": "https://p16-sign-va.tiktokcdn.com/tos-maliva-avt-0068/31672b0fc5b2724e2dec56d7be0edc68~c5_720x720.jpeg?x-expires=1650934800&x-signature=YpQkCo5eOYMb7v2CoMkV5Ci1Zqw%3D",
        "avatarThumb": "https://p16-sign-va.tiktokcdn.com/tos-maliva-avt-0068/31672b0fc5b2724e2dec56d7be0edc68~c5_100x100.jpeg?x-expires=1650934800&x-signature=VrghAm9qnvCk89uXm59FEaGMdlo%3D",
        "signature": "",
        "verified": false,
        "secUid": "MS4wLjABAAAAp4M_995yfrXpbnETv2lG_Sss10GpefcWNCmb54uB6hAY4EkNeXRNItUR5kzo96XT",
        "ftc": false,
        "relation": 0,
        "openFavorite": false,
        "commentSetting": 0,
        "duetSetting": 0,
        "stitchSetting": 0,
        "privateAccount": false,
        "secret": false,
        "isADVirtual": false,
        "roomId": ""
    },
    "stats": {
        "followerCount": 1102,
        "followingCount": 14,
        "heart": 7993,
        "heartCount": 7993,
        "videoCount": 51,
        "diggCount": 0
    },
    "itemList": []
}