{
    "user": {
        "id": "7043558100200457222",
        "shortId": "",
        "uniqueId": "albalb777",
        "nickname": "london london",
        "avatarLarger": "https://p77-sign-va.tiktokcdn.com/tos-maliva-avt-0068/0d149e95b010e4af736a2f842ecdf3bc~c5_1080x1080.jpeg?x-expires=1649905200&x-signature=7tSK3PWa4Y%2BjD8m0LNNubr1p48I%3D",
        "avatarMedium": "https://p16-sign-va.tiktokcdn.com/tos-maliva-avt-0068/0d149e95b010e4af736a2f842ecdf3bc~c5_720x720.jpeg?x-expires=1649905200&x-signature=ckbpd9AAgilZmsYHYiYX9VCxu5U%3D",
        "avatarThumb": "https://p16-sign-va.tiktokcdn.com/tos-maliva-avt-0068/0d149e95b010e4af736a2f842ecdf3bc~c5_100x100.jpeg?x-expires=1649905200&x-signature=1%2B2wgcZYPg0MBOZZumOjEwOWBxM%3D",
        "signature": "Looking to \ud83d\udccc the best \ud83d\udcaf comment",
        "createTime": 1639956236,
        "verified": false,
        "secUid": "MS4wLjABAAAA1SDFrNvKNdUHf6NLQgLlp57qBwcsoRwrUhYbCJaXG5Byd84dajOhTybtpA6JzWtw",
        "ftc": false,
        "relation": 0,
        "openFavorite": true,
        "commentSetting": 0,
        "duetSetting": 0,
        "stitchSetting": 0,
        "privateAccount": false,
        "secret": false,
        "isADVirtual": false,
        "roomId": ""
    },
    "stats": {
        "followerCount": 51300,
        "followingCount": 12,
        "heart": 634800,
        "heartCount": 634800,
        "videoCount": 64,
        "diggCount": 504
    },
    "itemList": []
}