{
    "id": "7088222849764314374",
    "desc": "#\u0434\u0443\u044d\u0442 \u0441 @pubg.ukrain5",
    "createTime": 1650355493,
    "video": {
        "id": "7088222849764314374",
        "height": 960,
        "width": 540,
        "duration": 11,
        "ratio": "720p",
        "cover": "https://p16-sign-va.tiktokcdn.com/obj/tos-maliva-p-0068/abeac5b499a14c0eb30b9dedd9f58e2d?x-expires=1650427200&x-signature=Hg0%2FqaI2KAXtDY7jj%2FZKShrswmE%3D",
        "originCover": "https://p16-sign-va.tiktokcdn.com/obj/tos-maliva-p-0068/1c7c70bd9d01494b87709047f60ca527_1650355493?x-expires=1650427200&x-signature=lnsXw%2BxzsxyZU5Oo2C3FWOHtcxg%3D",
        "dynamicCover": "https://p16-sign-va.tiktokcdn.com/obj/tos-maliva-p-0068/aaa71c6b1cc040b4aeb6ce08c33745c6_1650355494?x-expires=1650427200&x-signature=xIEXBs5feOdipQPV6wviRffTtP0%3D",
        "playAddr": "https://v16m-webapp.tiktokcdn-us.com/258315dfc232d4ba2e73e14f7cfde5dd/625f8a7a/video/tos/useast2a/tos-useast2a-pve-0068/de201cbc2022452bb1c95049fa5de075/?a=1988&br=1414&bt=707&cd=0%7C0%7C1%7C0&ch=0&cr=0&cs=0&cv=1&dr=0&ds=3&er=&ft=ebtHKH-qMyq8Zk1iwwe2NPq~fl7Gb&l=202204192222060101130061320102FF0C&lr=tiktok_m&mime_type=video_mp4&net=0&pl=0&qs=0&rc=ajdxa2c6Zjo5PDMzNzczM0ApNjNnNDc6aTxlN2U7OGU0ZWdsYjVfcjRvbmNgLS1kMTZzczIxLS4wLTUuYDUyMS1fL2A6Yw%3D%3D&vl=&vr=",
        "downloadAddr": "https://v16m-webapp.tiktokcdn-us.com/258315dfc232d4ba2e73e14f7cfde5dd/625f8a7a/video/tos/useast2a/tos-useast2a-pve-0068/de201cbc2022452bb1c95049fa5de075/?a=1988&br=1414&bt=707&cd=0%7C0%7C1%7C0&ch=0&cr=0&cs=0&cv=1&dr=0&ds=3&er=&ft=ebtHKH-qMyq8Zk1iwwe2NPq~fl7Gb&l=202204192222060101130061320102FF0C&lr=tiktok_m&mime_type=video_mp4&net=0&pl=0&qs=0&rc=ajdxa2c6Zjo5PDMzNzczM0ApNjNnNDc6aTxlN2U7OGU0ZWdsYjVfcjRvbmNgLS1kMTZzczIxLS4wLTUuYDUyMS1fL2A6Yw%3D%3D&vl=&vr=",
        "shareCover": [
            "",
            "https://p16-sign-va.tiktokcdn.com/tos-maliva-p-0068/1c7c70bd9d01494b87709047f60ca527_1650355493~tplv-tiktok-play.jpeg?x-expires=1651010400&x-signature=FtYuYxgM2XQRGzXQdFDw4YzVPZc%3D",
            "https://p16-sign-va.tiktokcdn.com/tos-maliva-p-0068/1c7c70bd9d01494b87709047f60ca527_1650355493~tplv-tiktokx-share-play.jpeg?x-expires=1651010400&x-signature=u6k7tFcnn7wPnrM6G73UW3Kfit0%3D"
        ],
        "reflowCover": "https://p16-sign-va.tiktokcdn.com/obj/tos-maliva-p-0068/abeac5b499a14c0eb30b9dedd9f58e2d?x-expires=1650427200&x-signature=Hg0%2FqaI2KAXtDY7jj%2FZKShrswmE%3D",
        "bitrate": 724371,
        "encodedType": "normal",
        "format": "mp4",
        "videoQuality": "normal",
        "encodeUserTag": ""
    },
    "author": {
        "id": "7054472738887287814",
        "uniqueId": "d.eniska1",
        "nickname": "\u0414\u0435\u043d\u0438\u0441 \u0420\u0430\u0434\u0430\u0443\u0446\u0430\u043d57",
        "avatarThumb": "https://p77-sign-va.tiktokcdn.com/tos-maliva-avt-0068/84769c544c80368ba59208a94053a9be~c5_100x100.jpeg?x-expires=1650578400&x-signature=kZiU7EskVk9NHcggjKSXbg6XuKY%3D",
        "avatarMedium": "https://p77-sign-va.tiktokcdn.com/tos-maliva-avt-0068/84769c544c80368ba59208a94053a9be~c5_720x720.jpeg?x-expires=1650578400&x-signature=0x4BuEBnK02C%2FRy74hTysE7lzIM%3D",
        "avatarLarger": "https://p77-sign-va.tiktokcdn.com/tos-maliva-avt-0068/84769c544c80368ba59208a94053a9be~c5_1080x1080.jpeg?x-expires=1650578400&x-signature=rqPIuvNrHNcAk%2BV7cWdMItXD19U%3D",
        "signature": "",
        "verified": false,
        "secUid": "MS4wLjABAAAAlTXan_Jv7-WF0L5ZBH4L72vC9MwHopf3vYXuI_LyKW4KlGFZHOGwxDNtntofwwll",
        "secret": false,
        "ftc": false,
        "relation": 0,
        "openFavorite": false,
        "commentSetting": 0,
        "duetSetting": 0,
        "stitchSetting": 0,
        "privateAccount": false
    },
    "music": {
        "id": "7085092304070920965",
        "title": "\u043e\u0440\u0438\u0433\u0456\u043d\u0430\u043b\u044c\u043d\u0438\u0439 \u0437\u0432\u0443\u043a",
        "playUrl": "https://sf16-ies-music-va.tiktokcdn.com/obj/musically-maliva-obj/7085092299713153798.mp3",
        "coverThumb": "https://p16-sign-va.tiktokcdn.com/tos-maliva-avt-0068/870ec919511efa95c31cc7d64489a0de~c5_100x100.jpeg?x-expires=1650578400&x-signature=kQTeWuJDeZiSeGE49aq0H29%2Bm4A%3D",
        "coverMedium": "https://p16-sign-va.tiktokcdn.com/tos-maliva-avt-0068/870ec919511efa95c31cc7d64489a0de~c5_720x720.jpeg?x-expires=1650578400&x-signature=TnufcsEVg8EzKw7SZZNpX23fa%2FQ%3D",
        "coverLarge": "https://p16-sign-va.tiktokcdn.com/tos-maliva-avt-0068/870ec919511efa95c31cc7d64489a0de~c5_1080x1080.jpeg?x-expires=1650578400&x-signature=JV455qc66vEv3a5O6fqvUaCc4Ao%3D",
        "authorName": "SLAVA UKRAINE",
        "original": true,
        "duration": 11,
        "album": ""
    },
    "challenges": [
        {
            "id": "4291788",
            "title": "\u0434\u0443\u044d\u0442",
            "desc": "",
            "profileThumb": "",
            "profileMedium": "",
            "profileLarger": "",
            "coverThumb": "",
            "coverMedium": "",
            "coverLarger": "",
            "isCommerce": false
        }
    ],
    "stats": {
        "diggCount": 246,
        "shareCount": 1,
        "commentCount": 2,
        "playCount": 2271
    },
    "duetInfo": {
        "duetFromId": "7085092299448896774"
    },
    "originalItem": false,
    "officalItem": false,
    "textExtra": [
        {
            "awemeId": "7085092299448896774",
            "start": 8,
            "end": 21,
            "hashtagName": "",
            "hashtagId": "",
            "type": 0,
            "userId": "6990070131528811526",
            "isCommerce": false,
            "userUniqueId": "pubg.ukrain5",
            "secUid": "MS4wLjABAAAAHabmsf5UHYSy4W2JzlRbjjt2utwTgb8ONUiFdo40CTWLfXaLKG6Sh_vb5XtxM3h-",
            "subType": 0
        },
        {
            "awemeId": "",
            "start": 0,
            "end": 5,
            "hashtagName": "\u0434\u0443\u044d\u0442",
            "hashtagId": "4291788",
            "type": 1,
            "userId": "",
            "isCommerce": false,
            "userUniqueId": "",
            "secUid": "",
            "subType": 0
        }
    ],
    "secret": false,
    "forFriend": false,
    "digged": false,
    "itemCommentStatus": 0,
    "showNotPass": false,
    "vl1": false,
    "itemMute": false,
    "authorStats": {
        "followingCount": 334,
        "followerCount": 1703,
        "heartCount": 4141,
        "videoCount": 30,
        "diggCount": 1157,
        "heart": 4141
    },
    "privateItem": false,
    "duetEnabled": true,
    "stitchEnabled": true,
    "shareEnabled": true,
    "stickersOnItem": [
        {
            "stickerType": 4,
            "stickerText": [
                "\u041a\u0443\u0434\u0430 \u0435\u0433\u043e",
                "\u0418\u0433\u043d\u043e\u0440-\u0430\u0434",
                "\u041b\u0430\u0439\u043a \u043f\u043e\u0442\u043f\u0438\u0441\u043a\u0430-\n-\u0440\u0430\u0439"
            ]
        }
    ],
    "isAd": false
}