{
    "user": {
        "id": "7053400905274278918",
        "shortId": "",
        "uniqueId": "_pypsen_009",
        "nickname": "Ukrain",
        "avatarLarger": "https://p16-sign-va.tiktokcdn.com/tos-maliva-avt-0068/d14c816c3a98ede6bcadf90582614b22~c5_1080x1080.jpeg?x-expires=1649120400&x-signature=iLxxENODaEPQNDPQGKAwCDx0Mpg%3D",
        "avatarMedium": "https://p16-sign-va.tiktokcdn.com/tos-maliva-avt-0068/d14c816c3a98ede6bcadf90582614b22~c5_720x720.jpeg?x-expires=1649120400&x-signature=0VS2Fx2%2BRxerc1NOlYgk9QPQcbc%3D",
        "avatarThumb": "https://p16-sign-va.tiktokcdn.com/tos-maliva-avt-0068/d14c816c3a98ede6bcadf90582614b22~c5_100x100.jpeg?x-expires=1649120400&x-signature=ZS0Bnt11I0f4VV%2BzcAv9DCzJryA%3D",
        "signature": "\u0425\u0442\u043e \u0437\u0430 \u0423\u043a\u0440\u0430\u0457\u043d\u0443?",
        "createTime": 1644214884,
        "verified": false,
        "secUid": "MS4wLjABAAAAesqj9wqxzbM3P0tm8hRRPx4dEXPO0cV0xhJEYrYGzockK6OPNr9yb7u2QEJt3OcU",
        "ftc": false,
        "relation": 0,
        "openFavorite": false,
        "commentSetting": 0,
        "duetSetting": 0,
        "stitchSetting": 0,
        "privateAccount": false,
        "secret": false,
        "isADVirtual": false,
        "roomId": ""
    },
    "stats": {
        "followerCount": 5911,
        "followingCount": 167,
        "heart": 26700,
        "heartCount": 26700,
        "videoCount": 232,
        "diggCount": 0
    },
    "itemList": []
}