{
    "id": "7082804914006527238",
    "desc": "\ud83d\udc94\ud83c\uddfa\ud83c\udde6 #\u0440\u0435\u043a\u043e\u043c\u0435\u043d\u0434\u0430\u0446\u0438\u0438 #\u0440\u0435\u043a #ukraine\ud83c\uddfa\ud83c\udde6",
    "createTime": 1649094028,
    "video": {
        "id": "7082804914006527238",
        "height": 770,
        "width": 576,
        "duration": 10,
        "ratio": "720p",
        "cover": "https://p16-sign-va.tiktokcdn.com/obj/tos-maliva-p-0068/62a262cc955641028cdf204a542fc123?x-expires=1649131200&x-signature=usJ62%2F9g0ajfjxV%2FM8gLRoh7IOw%3D",
        "originCover": "https://p16-sign-va.tiktokcdn.com/obj/tos-maliva-p-0068/8450312088f44d459f8439a43726e8e9_1649094029?x-expires=1649131200&x-signature=0hY7J8PZIuzX4p%2BblFqIH3UNJW0%3D",
        "dynamicCover": "https://p16-sign-va.tiktokcdn.com/obj/tos-maliva-p-0068/5446a240fe6e4513a02ec7adf9a0946f_1649094029?x-expires=1649131200&x-signature=ZD2P%2FY29BgHm7NXnE64vCBTzuUg%3D",
        "playAddr": "https://v16m-webapp.tiktokcdn-us.com/203a7ad0568abdbfafe418a38bb71735/624bc029/video/tos/useast2a/tos-useast2a-pve-0068/c9190dfeea6845f4897af378c47e2671/?a=1988&br=2478&bt=1239&cd=0%7C0%7C1%7C0&ch=0&cr=0&cs=0&cv=1&dr=0&ds=3&er=&ft=XY53A3E7nz7Th8FeqDXq&l=2022040422055201011313523317852E7F&lr=tiktok_m&mime_type=video_mp4&net=0&pl=0&qs=0&rc=ajNoaDM6ZjVsPDMzNzczM0ApN2ZmZTk5ZTw8NzU2NzRpNGdjbDMwcjQwbzJgLS1kMTZzcy8uYjMzMDUzMi8wNi4xYF46Yw%3D%3D&vl=&vr=",
        "downloadAddr": "https://v16m-webapp.tiktokcdn-us.com/203a7ad0568abdbfafe418a38bb71735/624bc029/video/tos/useast2a/tos-useast2a-pve-0068/c9190dfeea6845f4897af378c47e2671/?a=1988&br=2478&bt=1239&cd=0%7C0%7C1%7C0&ch=0&cr=0&cs=0&cv=1&dr=0&ds=3&er=&ft=XY53A3E7nz7Th8FeqDXq&l=2022040422055201011313523317852E7F&lr=tiktok_m&mime_type=video_mp4&net=0&pl=0&qs=0&rc=ajNoaDM6ZjVsPDMzNzczM0ApN2ZmZTk5ZTw8NzU2NzRpNGdjbDMwcjQwbzJgLS1kMTZzcy8uYjMzMDUzMi8wNi4xYF46Yw%3D%3D&vl=&vr=",
        "shareCover": [
            "",
            "https://p16-sign-va.tiktokcdn.com/tos-maliva-p-0068/8450312088f44d459f8439a43726e8e9_1649094029~tplv-tiktok-play.jpeg?x-expires=1649714400&x-signature=hKPu9251kBUJFBse7uu%2B%2Fn8hCx0%3D",
            "https://p16-sign-va.tiktokcdn.com/tos-maliva-p-0068/8450312088f44d459f8439a43726e8e9_1649094029~tplv-tiktokx-share-play.jpeg?x-expires=1649714400&x-signature=Zlfe7QKGQbM8V6Q7HPuDXbTVIcE%3D"
        ],
        "reflowCover": "https://p16-sign-va.tiktokcdn.com/obj/tos-maliva-p-0068/62a262cc955641028cdf204a542fc123?x-expires=1649131200&x-signature=usJ62%2F9g0ajfjxV%2FM8gLRoh7IOw%3D",
        "bitrate": 1269048,
        "encodedType": "normal",
        "format": "mp4",
        "videoQuality": "normal",
        "encodeUserTag": ""
    },
    "author": {
        "id": "6871640126281286658",
        "uniqueId": "steshakalmakan",
        "nickname": "steshakalmakan",
        "avatarThumb": "https://p16-sign-va.tiktokcdn.com/tos-maliva-avt-0068/f875bc44518a9b3233d05b730a697479~c5_100x100.jpeg?x-expires=1649196000&x-signature=gtxgO4O0yy5mNN0%2FhoTN17TJ19o%3D",
        "avatarMedium": "https://p16-sign-va.tiktokcdn.com/tos-maliva-avt-0068/f875bc44518a9b3233d05b730a697479~c5_720x720.jpeg?x-expires=1649196000&x-signature=8UWSJn1dOyTRNP1UMV%2FSgYRkLNM%3D",
        "avatarLarger": "https://p16-sign-va.tiktokcdn.com/tos-maliva-avt-0068/f875bc44518a9b3233d05b730a697479~c5_1080x1080.jpeg?x-expires=1649196000&x-signature=Sz6M2CGXJwsWSWhxhZXq%2BO%2BJOSk%3D",
        "signature": "\ud835\udce2\ud835\udcfd\ud835\udcee\ud835\udcfc\ud835\udcf1\ud835\udcea \n\n\ud835\udcde\ud835\udced\ud835\udcee\ud835\udcfc\ud835\udcfc\ud835\udcea , \ud835\udce4\ud835\udcd0\ud83c\uddfa\ud83c\udde6",
        "verified": false,
        "secUid": "MS4wLjABAAAApUTjFzXwV-6UTOfgBVf8d2RgvSz1eO_zHPO6wz9njy5mGaUoMkCXvInwoJ5dnHrM",
        "secret": false,
        "ftc": false,
        "relation": 0,
        "openFavorite": false,
        "commentSetting": 0,
        "duetSetting": 1,
        "stitchSetting": 1,
        "privateAccount": false
    },
    "music": {
        "id": "7080262226011409157",
        "title": "\u043e\u0440\u0438\u0433\u0438\u043d\u0430\u043b\u044c\u043d\u044b\u0439 \u0437\u0432\u0443\u043a",
        "playUrl": "https://sf16-ies-music-va.tiktokcdn.com/obj/musically-maliva-obj/7080262217882422021.mp3",
        "coverThumb": "https://p77-sign-va.tiktokcdn.com/tos-maliva-avt-0068/cc4e5a2fcf5b3b6c2ddbb69750e79b54~c5_100x100.jpeg?x-expires=1649196000&x-signature=O5QwkmIux0F2%2FxPl%2FM6kYJiHUNU%3D",
        "coverMedium": "https://p77-sign-va.tiktokcdn.com/tos-maliva-avt-0068/cc4e5a2fcf5b3b6c2ddbb69750e79b54~c5_720x720.jpeg?x-expires=1649196000&x-signature=CTU2I9%2F6ESvIEvek6TowyAzjelA%3D",
        "coverLarge": "https://p16-sign-va.tiktokcdn.com/tos-maliva-avt-0068/cc4e5a2fcf5b3b6c2ddbb69750e79b54~c5_1080x1080.jpeg?x-expires=1649196000&x-signature=lvcRX%2B%2F8oeZM0PuUL2Qbb8CHmY8%3D",
        "authorName": "_da_na_aa.__",
        "original": true,
        "duration": 11,
        "album": ""
    },
    "challenges": [
        {
            "id": "49711363",
            "title": "\u0440\u0435\u043a\u043e\u043c\u0435\u043d\u0434\u0430\u0446\u0438\u0438",
            "desc": "",
            "profileThumb": "",
            "profileMedium": "",
            "profileLarger": "",
            "coverThumb": "",
            "coverMedium": "",
            "coverLarger": "",
            "isCommerce": false
        },
        {
            "id": "50321361",
            "title": "\u0440\u0435\u043a",
            "desc": "",
            "profileThumb": "",
            "profileMedium": "",
            "profileLarger": "",
            "coverThumb": "",
            "coverMedium": "",
            "coverLarger": "",
            "isCommerce": false
        },
        {
            "id": "1592381310170118",
            "title": "ukraine\ud83c\uddfa\ud83c\udde6",
            "desc": "",
            "profileThumb": "",
            "profileMedium": "",
            "profileLarger": "",
            "coverThumb": "",
            "coverMedium": "",
            "coverLarger": "",
            "isCommerce": false
        }
    ],
    "stats": {
        "diggCount": 115,
        "shareCount": 0,
        "commentCount": 2,
        "playCount": 1716
    },
    "duetInfo": {
        "duetFromId": "0"
    },
    "originalItem": false,
    "officalItem": false,
    "textExtra": [
        {
            "awemeId": "",
            "start": 7,
            "end": 20,
            "hashtagName": "\u0440\u0435\u043a\u043e\u043c\u0435\u043d\u0434\u0430\u0446\u0438\u0438",
            "hashtagId": "49711363",
            "type": 1,
            "userId": "",
            "isCommerce": false,
            "userUniqueId": "",
            "secUid": "",
            "subType": 0
        },
        {
            "awemeId": "",
            "start": 21,
            "end": 25,
            "hashtagName": "\u0440\u0435\u043a",
            "hashtagId": "50321361",
            "type": 1,
            "userId": "",
            "isCommerce": false,
            "userUniqueId": "",
            "secUid": "",
            "subType": 0
        },
        {
            "awemeId": "",
            "start": 26,
            "end": 38,
            "hashtagName": "ukraine\ud83c\uddfa\ud83c\udde6",
            "hashtagId": "1592381310170118",
            "type": 1,
            "userId": "",
            "isCommerce": false,
            "userUniqueId": "",
            "secUid": "",
            "subType": 0
        }
    ],
    "secret": false,
    "forFriend": false,
    "digged": false,
    "itemCommentStatus": 0,
    "showNotPass": false,
    "vl1": false,
    "itemMute": false,
    "authorStats": {
        "followingCount": 93,
        "followerCount": 2970,
        "heartCount": 163900,
        "videoCount": 80,
        "diggCount": 2258,
        "heart": 163900
    },
    "privateItem": false,
    "duetEnabled": true,
    "stitchEnabled": true,
    "shareEnabled": true,
    "stickersOnItem": [
        {
            "stickerType": 4,
            "stickerText": [
                "\u0436\u0438\u0432\u0435\u043c \u043e\u0434\u0438\u043d \u0440\u0430\u0437",
                "\u043d\u0430\u0434\u043e \u0431\u044b ",
                "\u0435\u0433\u043e \u0437\u0430\u043f\u043e\u043c\u043d\u0438\u0442\u044c\u2764\ufe0f"
            ]
        }
    ],
    "isAd": false
}