{
    "user": {
        "id": "6817365289531343877",
        "shortId": "",
        "uniqueId": "florian.mjsk",
        "nickname": "Florian",
        "avatarLarger": "https://p16-sign-va.tiktokcdn.com/tos-maliva-avt-0068/55f00ad69771c7d0fef13312ffc513b4~c5_1080x1080.jpeg?x-expires=1648069200&x-signature=r2tnf%2FHUJn3uVGVpzetKDvqun7g%3D",
        "avatarMedium": "https://p16-sign-va.tiktokcdn.com/tos-maliva-avt-0068/55f00ad69771c7d0fef13312ffc513b4~c5_720x720.jpeg?x-expires=1648069200&x-signature=CJOfOXuoqPOJm0qh7Xg5CZVtV08%3D",
        "avatarThumb": "https://p16-sign-va.tiktokcdn.com/tos-maliva-avt-0068/55f00ad69771c7d0fef13312ffc513b4~c5_100x100.jpeg?x-expires=1648069200&x-signature=DWGhZ4fAauHUG29q%2BvOnMEonhkA%3D",
        "signature": "lille | 17 \n121k bg\u2019s \ud83d\ude3c\ninsta : florian.mjsk \ud83d\udcf8",
        "createTime": 1587292921,
        "verified": false,
        "secUid": "MS4wLjABAAAAWbiL0bYMj0kqTvR9e3Q83L-sWpBzsrPxQhjDYuUT5e0CKBQrFAVkvoONU64KheKV",
        "ftc": false,
        "relation": 0,
        "openFavorite": false,
        "commentSetting": 0,
        "duetSetting": 1,
        "stitchSetting": 1,
        "privateAccount": false,
        "secret": false,
        "isADVirtual": false,
        "roomId": ""
    },
    "stats": {
        "followerCount": 121000,
        "followingCount": 31,
        "heart": 4800000,
        "heartCount": 4800000,
        "videoCount": 522,
        "diggCount": 0
    },
    "itemList": []
}