{
    "user": {
        "id": "6794076818981291013",
        "shortId": "",
        "uniqueId": "movieditsvillvein",
        "nickname": "movie-edits-villvein",
        "avatarLarger": "https://p16-sign-va.tiktokcdn.com/tos-maliva-avt-0068/8e9dea64c8f6260b18d00057552bcd15~c5_1080x1080.jpeg?x-expires=1648764000&x-signature=VOVWQqymicC%2FkqpyNykFk9kDUiA%3D",
        "avatarMedium": "https://p16-sign-va.tiktokcdn.com/tos-maliva-avt-0068/8e9dea64c8f6260b18d00057552bcd15~c5_720x720.jpeg?x-expires=1648764000&x-signature=UBAYinxamnlg9GuKucwEcAmxQik%3D",
        "avatarThumb": "https://p16-sign-va.tiktokcdn.com/tos-maliva-avt-0068/8e9dea64c8f6260b18d00057552bcd15~c5_100x100.jpeg?x-expires=1648764000&x-signature=OzCfufvetuJjk4I5PC%2Fy%2B0zgzgU%3D",
        "signature": "\ud83c\udfa5 \ud83c\udf7f",
        "createTime": 1581840678,
        "verified": false,
        "secUid": "MS4wLjABAAAAeCTIcBcWa6jIwGbSnI9AYYCniqeK56AjUGQJu60fzccGdjEd0qsYDL28hFFRp3vd",
        "ftc": false,
        "relation": 0,
        "openFavorite": false,
        "commentSetting": 0,
        "duetSetting": 0,
        "stitchSetting": 0,
        "privateAccount": false,
        "secret": false,
        "isADVirtual": false,
        "roomId": ""
    },
    "stats": {
        "followerCount": 21200,
        "followingCount": 10000,
        "heart": 753200,
        "heartCount": 753200,
        "videoCount": 43,
        "diggCount": 0
    },
    "itemList": []
}