{
    "user": {
        "id": "6725464211156403205",
        "shortId": "",
        "uniqueId": "marcus.dipaola",
        "nickname": "Marcus DiPaola",
        "avatarLarger": "https://p16-sign-va.tiktokcdn.com/tos-maliva-avt-0068/3b9f84a5ce2435d60d9384ea1af9abcf~c5_1080x1080.jpeg?x-expires=1647050400&x-signature=ItR2yyt3d4wDvj4iLjw22xrNY9s%3D",
        "avatarMedium": "https://p16-sign-va.tiktokcdn.com/tos-maliva-avt-0068/3b9f84a5ce2435d60d9384ea1af9abcf~c5_720x720.jpeg?x-expires=1647050400&x-signature=bcT5DR1i9h5CbrUKIQ2wxn9yZhg%3D",
        "avatarThumb": "https://p16-sign-va.tiktokcdn.com/tos-maliva-avt-0068/3b9f84a5ce2435d60d9384ea1af9abcf~c5_100x100.jpeg?x-expires=1647050400&x-signature=puUkEXPkg90%2Bf7%2BGX5t1pksKHc8%3D",
        "signature": "Host of News 101 on Snapchat, anchoring news as it breaks here on TikTok.",
        "createTime": 1565894253,
        "verified": true,
        "secUid": "MS4wLjABAAAAt_iVPv2xFHOnKgw70t5YNDVrDMzV-V71959z98rV441muJW6ozh0SGIIxrq5cHIS",
        "ftc": false,
        "relation": 0,
        "openFavorite": false,
        "bioLink": {
            "link": "https://linktr.ee/marcusdipaola",
            "risk": 3
        },
        "commentSetting": 0,
        "duetSetting": 0,
        "stitchSetting": 0,
        "privateAccount": false,
        "secret": false,
        "isADVirtual": false,
        "roomId": ""
    },
    "stats": {
        "followerCount": 3500000,
        "followingCount": 0,
        "heart": 273200000,
        "heartCount": 273200000,
        "videoCount": 3059,
        "diggCount": 0
    },
    "itemList": []
}