{
    "id": "7088311447213591854",
    "desc": "#slavaukraine",
    "createTime": 1650376118,
    "video": {
        "id": "7088311447213591854",
        "height": 1024,
        "width": 576,
        "duration": 177,
        "ratio": "720p",
        "cover": "https://p19-sign.tiktokcdn-us.com/obj/tos-useast5-p-0068-tx/e4ddce0269b54a89a9991f0c53ab7d68?x-expires=1650427200&x-signature=mPono%2FrMg2bEbxHkNB0Ulwm1yOE%3D",
        "originCover": "https://p19-sign.tiktokcdn-us.com/obj/tos-useast5-p-0068-tx/ffdb261e95fb44a1a85bf85e108ed885_1650376119?x-expires=1650427200&x-signature=83XiChps3uQ0Px%2FCtMlSP6NBIXQ%3D",
        "dynamicCover": "https://p16-sign.tiktokcdn-us.com/obj/tos-useast5-p-0068-tx/87a406523bbb411e8fc3c7b14411f602_1650376119?x-expires=1650427200&x-signature=xWlmmA7IyTbXdhWOKXxNLkSyZ34%3D",
        "playAddr": "https://v16m-webapp.tiktokcdn-us.com/9ed22b9c9078311a61f923cd13b6988a/625f8a3d/video/tos/useast5/tos-useast5-pve-0068-tx/d4dfdaae28a34b0490680fe39eb36472/?a=1988&br=1894&bt=947&cd=0%7C0%7C0%7C0&ch=0&cr=0&cs=0&dr=0&ds=3&er=&ft=ebtHKH-qMyq8ZyHiwwe2Nh3-fl7Gb&l=202204192218200101131351350A0B8BD4&lr=tiktok_m&mime_type=video_mp4&net=0&pl=0&qs=0&rc=anRrdmQ6ZmZlPDMzZzczNEApPGg7PDQzZjw6NzRnaDZmPGdkbWsvcjRvbWNgLS1kMS9zczEvYDJgNi80MC0vM2BgYS46Yw%3D%3D&vl=&vr=",
        "downloadAddr": "https://v16m-webapp.tiktokcdn-us.com/9ed22b9c9078311a61f923cd13b6988a/625f8a3d/video/tos/useast5/tos-useast5-pve-0068-tx/d4dfdaae28a34b0490680fe39eb36472/?a=1988&br=1894&bt=947&cd=0%7C0%7C0%7C0&ch=0&cr=0&cs=0&dr=0&ds=3&er=&ft=ebtHKH-qMyq8ZyHiwwe2Nh3-fl7Gb&l=202204192218200101131351350A0B8BD4&lr=tiktok_m&mime_type=video_mp4&net=0&pl=0&qs=0&rc=anRrdmQ6ZmZlPDMzZzczNEApPGg7PDQzZjw6NzRnaDZmPGdkbWsvcjRvbWNgLS1kMS9zczEvYDJgNi80MC0vM2BgYS46Yw%3D%3D&vl=&vr=",
        "shareCover": [
            "",
            "https://p16-sign.tiktokcdn-us.com/tos-useast5-p-0068-tx/ffdb261e95fb44a1a85bf85e108ed885_1650376119~tplv-tiktok-play.jpeg?x-expires=1651010400&x-signature=Bwh2f6gg04LJuQkr%2FIT4%2BRM%2FpKI%3D",
            "https://p16-sign.tiktokcdn-us.com/tos-useast5-p-0068-tx/ffdb261e95fb44a1a85bf85e108ed885_1650376119~tplv-tiktokx-share-play.jpeg?x-expires=1651010400&x-signature=KmNwFOLDzuvRWpJBftmY97XgcY8%3D"
        ],
        "reflowCover": "https://p16-sign.tiktokcdn-us.com/obj/tos-useast5-p-0068-tx/e4ddce0269b54a89a9991f0c53ab7d68?x-expires=1650427200&x-signature=szXY0ScDjQZLLDsbRgkj0y6oP00%3D",
        "bitrate": 969840,
        "encodedType": "normal",
        "format": "mp4",
        "videoQuality": "normal",
        "encodeUserTag": ""
    },
    "author": {
        "id": "7061996293923439662",
        "uniqueId": "brianmiller2098",
        "nickname": "Brian Miller2098",
        "avatarThumb": "https://p19-sign.tiktokcdn-us.com/tos-useast5-avt-0068-tx/7061999794130010159~c5_100x100.jpeg?x-expires=1650578400&x-signature=8ySLZX2zxt6CxYd8YSAVL2jxdnY%3D",
        "avatarMedium": "https://p16-sign.tiktokcdn-us.com/tos-useast5-avt-0068-tx/7061999794130010159~c5_720x720.jpeg?x-expires=1650578400&x-signature=wCHH6Ff9hDfz%2FWPB3JNwf4PFP4k%3D",
        "avatarLarger": "https://p16-sign.tiktokcdn-us.com/tos-useast5-avt-0068-tx/7061999794130010159~c5_1080x1080.jpeg?x-expires=1650578400&x-signature=aZOSnaureNQsoxjX8YwE9DhKk2U%3D",
        "signature": "See link below for my POV on war in Ukraine\ud83c\uddf7\ud83c\uddfc\ud83c\uddfa\ud83c\uddf8\u270c\ud83c\udffb\ud83d\udd25\ud83c\udf08\ud83e\udd19\ud83c\udffb",
        "verified": false,
        "secUid": "MS4wLjABAAAA4zLxVI_Ckn57wuXKo83erHMUA8jF6f4Ggdn1hZk1Ce1ZL-IbkYdF_9KmX3DIszS0",
        "secret": false,
        "ftc": false,
        "relation": 0,
        "openFavorite": false,
        "commentSetting": 0,
        "duetSetting": 0,
        "stitchSetting": 0,
        "privateAccount": false
    },
    "music": {
        "id": "7088312169900903210",
        "title": "original sound",
        "playUrl": "https://sf19.tiktokcdn-us.com/obj/ies-music-tx/7088312225252952878.mp3",
        "coverThumb": "https://p19-sign.tiktokcdn-us.com/tos-useast5-avt-0068-tx/7061999794130010159~c5_100x100.jpeg?x-expires=1650578400&x-signature=8ySLZX2zxt6CxYd8YSAVL2jxdnY%3D",
        "coverMedium": "https://p16-sign.tiktokcdn-us.com/tos-useast5-avt-0068-tx/7061999794130010159~c5_720x720.jpeg?x-expires=1650578400&x-signature=wCHH6Ff9hDfz%2FWPB3JNwf4PFP4k%3D",
        "coverLarge": "https://p16-sign.tiktokcdn-us.com/tos-useast5-avt-0068-tx/7061999794130010159~c5_1080x1080.jpeg?x-expires=1650578400&x-signature=aZOSnaureNQsoxjX8YwE9DhKk2U%3D",
        "authorName": "Brian Miller2098",
        "original": true,
        "duration": 177,
        "album": ""
    },
    "challenges": [
        {
            "id": "1616838716545030",
            "title": "slavaukraine",
            "desc": "",
            "profileThumb": "",
            "profileMedium": "",
            "profileLarger": "",
            "coverThumb": "",
            "coverMedium": "",
            "coverLarger": "",
            "isCommerce": false
        }
    ],
    "stats": {
        "diggCount": 36,
        "shareCount": 0,
        "commentCount": 4,
        "playCount": 388
    },
    "duetInfo": {
        "duetFromId": "0"
    },
    "originalItem": false,
    "officalItem": false,
    "textExtra": [
        {
            "awemeId": "",
            "start": 0,
            "end": 13,
            "hashtagName": "slavaukraine",
            "hashtagId": "1616838716545030",
            "type": 1,
            "userId": "",
            "isCommerce": false,
            "userUniqueId": "",
            "secUid": "",
            "subType": 0
        }
    ],
    "secret": false,
    "forFriend": false,
    "digged": false,
    "itemCommentStatus": 0,
    "showNotPass": false,
    "vl1": false,
    "itemMute": false,
    "authorStats": {
        "followingCount": 3,
        "followerCount": 2278,
        "heartCount": 30600,
        "videoCount": 224,
        "diggCount": 21,
        "heart": 30600
    },
    "privateItem": false,
    "duetEnabled": true,
    "stitchEnabled": true,
    "shareEnabled": true,
    "stickersOnItem": [
        {
            "stickerType": 4,
            "stickerText": [
                "The West needs \nto realize just \nhow nuts \nPutin has \nbecome. "
            ]
        }
    ],
    "isAd": false
}