{
    "id": "7083513956714745094",
    "desc": "\u043a\u0430\u0447\u0435\u0441\u0442\u0432\u043e.. #bye2020 #ukraine #followme #n1kosup #popularpic #\u0430\u043d\u0434\u0440\u0435\u0439 #\u0432\u0435\u0441\u043d\u0430 #\u043b\u0435\u0442\u043e #tdm #Ukraine #n1 #\u0432\u0440\u0435\u043a #\u0440\u0435\u043a\u043e\u043c\u0435\u043d\u0434\u0430\u0446\u0438\u0438",
    "createTime": 1649259115,
    "video": {
        "id": "7083513956714745094",
        "height": 576,
        "width": 1276,
        "duration": 10,
        "ratio": "720p",
        "cover": "https://p16-sign-va.tiktokcdn.com/obj/tos-maliva-p-0068/2d97b7fd4fc2422c9fdfaf4ed2dce005?x-expires=1649307600&x-signature=y5WTAQkTHTherJ8tlg5sRZ12F%2Bo%3D",
        "originCover": "https://p16-sign-va.tiktokcdn.com/obj/tos-maliva-p-0068/8e7cd192346445c2b87246ce9cae5862_1649259116?x-expires=1649307600&x-signature=J%2F9KXXJzldwqE6AUkSeqXlENOg8%3D",
        "dynamicCover": "https://p16-sign-va.tiktokcdn.com/obj/tos-maliva-p-0068/5ba0ad376d7c4f01b81b43cde8097599_1649259117?x-expires=1649307600&x-signature=H%2F3xyUBd7j%2BVuJkPQ205ZLJzy2A%3D",
        "playAddr": "https://v16m-webapp.tiktokcdn-us.com/e369220c80125f56bb5d94a16e5b8706/624e73f9/video/tos/useast2a/tos-useast2a-pve-0068/8f61c8fa79614baa8f6a30f6411a3cc4/?a=1988&br=7548&bt=3774&cd=0%7C0%7C0%7C0&ch=0&cr=0&cs=0&dr=0&ds=3&er=&ft=XY53A3E7nz7ThLsSSDXq&l=202204062317350101131351051DAC67F3&lr=tiktok_m&mime_type=video_mp4&net=0&pl=0&qs=0&rc=amw2bDk6ZjZ1PDMzNzczM0ApaTs4OWQ4NWRpNztmZDllZmdobHFwcjRnMDNgLS1kMTZzcy0xXjFeX2IuL2FjMi4xLi46Yw%3D%3D&vl=&vr=",
        "downloadAddr": "https://v16m-webapp.tiktokcdn-us.com/e369220c80125f56bb5d94a16e5b8706/624e73f9/video/tos/useast2a/tos-useast2a-pve-0068/8f61c8fa79614baa8f6a30f6411a3cc4/?a=1988&br=7548&bt=3774&cd=0%7C0%7C0%7C0&ch=0&cr=0&cs=0&dr=0&ds=3&er=&ft=XY53A3E7nz7ThLsSSDXq&l=202204062317350101131351051DAC67F3&lr=tiktok_m&mime_type=video_mp4&net=0&pl=0&qs=0&rc=amw2bDk6ZjZ1PDMzNzczM0ApaTs4OWQ4NWRpNztmZDllZmdobHFwcjRnMDNgLS1kMTZzcy0xXjFeX2IuL2FjMi4xLi46Yw%3D%3D&vl=&vr=",
        "shareCover": [
            "",
            "https://p16-sign-va.tiktokcdn.com/tos-maliva-p-0068/8e7cd192346445c2b87246ce9cae5862_1649259116~tplv-tiktok-play.jpeg?x-expires=1649890800&x-signature=4FysLPGrEVeglvopiQqhUK1YKgc%3D",
            "https://p16-sign-va.tiktokcdn.com/tos-maliva-p-0068/8e7cd192346445c2b87246ce9cae5862_1649259116~tplv-tiktokx-share-play.jpeg?x-expires=1649890800&x-signature=OzuggAm45HXcb2ktz%2FwjqzK6ypI%3D"
        ],
        "reflowCover": "https://p16-sign-va.tiktokcdn.com/obj/tos-maliva-p-0068/2d97b7fd4fc2422c9fdfaf4ed2dce005?x-expires=1649307600&x-signature=y5WTAQkTHTherJ8tlg5sRZ12F%2Bo%3D",
        "bitrate": 3865346,
        "encodedType": "normal",
        "format": "mp4",
        "videoQuality": "normal",
        "encodeUserTag": ""
    },
    "author": {
        "id": "7076512274462213126",
        "uniqueId": "deniksxxx",
        "nickname": "\u0431\u0430\u0431\u0438\u0434\u0436\u043e\u043d",
        "avatarThumb": "https://p16-sign-va.tiktokcdn.com/tos-maliva-avt-0068/204ef3e0ee66d4b744137225d9462fc1~c5_100x100.jpeg?x-expires=1649372400&x-signature=3ZfgXv6%2Fygvh4pmnYjbA7Yf3Qu4%3D",
        "avatarMedium": "https://p16-sign-va.tiktokcdn.com/tos-maliva-avt-0068/204ef3e0ee66d4b744137225d9462fc1~c5_720x720.jpeg?x-expires=1649372400&x-signature=3gt3phJYZZ2UjrO%2FO2K43QKbgOQ%3D",
        "avatarLarger": "https://p16-sign-va.tiktokcdn.com/tos-maliva-avt-0068/204ef3e0ee66d4b744137225d9462fc1~c5_1080x1080.jpeg?x-expires=1649372400&x-signature=SQJ1JDounyG935ZFrPDKFASQO0U%3D",
        "signature": "\ud835\udde3\ud835\ude02\ud835\uddef\ud835\uddf4 \ud835\uddfa\ud835\uddfc\ud835\uddef\ud835\uddf6\ud835\uddf9\ud835\uddf2\n\ud835\udff0 \ud835\uddf3\ud835\uddf6\ud835\uddfb\ud835\uddf4\ud835\uddf2\ud835\uddff\ud835\ude00\n\ud83c\uddfa\ud83c\udde6/\ud83c\uddf5\ud83c\uddf1",
        "verified": false,
        "secUid": "MS4wLjABAAAAj4G8BW7bON0jw1ojQJXYo2tu-3SLLMHHSY0fNCpHcbTadw2uqJ4Rd9VGfADlw9gA",
        "secret": false,
        "ftc": false,
        "relation": 0,
        "openFavorite": false,
        "commentSetting": 0,
        "duetSetting": 0,
        "stitchSetting": 0,
        "privateAccount": false
    },
    "music": {
        "id": "7061287193192565506",
        "title": "\u043e\u0440\u0438\u0433\u0438\u043d\u0430\u043b\u044c\u043d\u044b\u0439 \u0437\u0432\u0443\u043a",
        "playUrl": "https://sf16-ies-music-sg.tiktokcdn.com/obj/tiktok-obj/7061287197252881153.mp3",
        "coverThumb": "https://p16-sign-sg.tiktokcdn.com/aweme/100x100/tos-alisg-avt-0068/392a1566699fde01e52625a986be2955.jpeg?x-expires=1649372400&x-signature=9AsuLFogQBObEOr3fpkwtIzHmSE%3D",
        "coverMedium": "https://p16-sign-sg.tiktokcdn.com/aweme/720x720/tos-alisg-avt-0068/392a1566699fde01e52625a986be2955.jpeg?x-expires=1649372400&x-signature=iMUefxtFbtx6V4jHkHCuUw9XzGU%3D",
        "coverLarge": "https://p58-sign-sg.tiktokcdn.com/aweme/1080x1080/tos-alisg-avt-0068/392a1566699fde01e52625a986be2955.jpeg?x-expires=1649372400&x-signature=E%2BECzyVsdQ7Kb4iYi5GrsCgllyg%3D",
        "authorName": "\u2764\ufe0f\u200d\ud83d\udd25\u0412\u0438\u0434\u0435\u043e \u0441\u0442\u0430\u0440\u2764\ufe0f\u200d\ud83d\udd25",
        "original": true,
        "duration": 10,
        "album": ""
    },
    "challenges": [
        {
            "id": "1640302203126790",
            "title": "Bye2020",
            "desc": "See ya, 2020.",
            "profileThumb": "https://p16-amd-va.tiktokcdn.com/obj/musically-maliva-obj/92b4fa02fc5f0d54526d03dedf5dac1d",
            "profileMedium": "https://p16-amd-va.tiktokcdn.com/obj/musically-maliva-obj/92b4fa02fc5f0d54526d03dedf5dac1d",
            "profileLarger": "https://p16-amd-va.tiktokcdn.com/obj/musically-maliva-obj/92b4fa02fc5f0d54526d03dedf5dac1d",
            "coverThumb": "",
            "coverMedium": "",
            "coverLarger": "",
            "isCommerce": false
        },
        {
            "id": "451042",
            "title": "ukraine",
            "desc": "",
            "profileThumb": "",
            "profileMedium": "",
            "profileLarger": "",
            "coverThumb": "",
            "coverMedium": "",
            "coverLarger": "",
            "isCommerce": false
        },
        {
            "id": "6856",
            "title": "followme",
            "desc": "",
            "profileThumb": "",
            "profileMedium": "",
            "profileLarger": "",
            "coverThumb": "",
            "coverMedium": "",
            "coverLarger": "",
            "isCommerce": false
        },
        {
            "id": "1650546899645445",
            "title": "n1kosup",
            "desc": "",
            "profileThumb": "",
            "profileMedium": "",
            "profileLarger": "",
            "coverThumb": "",
            "coverMedium": "",
            "coverLarger": "",
            "isCommerce": false
        },
        {
            "id": "552988",
            "title": "popularpic",
            "desc": "",
            "profileThumb": "",
            "profileMedium": "",
            "profileLarger": "",
            "coverThumb": "",
            "coverMedium": "",
            "coverLarger": "",
            "isCommerce": false
        },
        {
            "id": "5981203",
            "title": "\u0430\u043d\u0434\u0440\u0435\u0439",
            "desc": "",
            "profileThumb": "",
            "profileMedium": "",
            "profileLarger": "",
            "coverThumb": "",
            "coverMedium": "",
            "coverLarger": "",
            "isCommerce": false
        },
        {
            "id": "5681299",
            "title": "\u0432\u0435\u0441\u043d\u0430",
            "desc": "\u041a\u0430\u043a \u0432\u0430\u0441 \u0432\u0434\u043e\u0445\u043d\u043e\u0432\u043b\u044f\u0435\u0442 #\u0432\u0435\u0441\u043d\u0430 \ud83e\udd29 ? \u041f\u043e\u0434\u0435\u043b\u0438\u0442\u0435\u0441\u044c \u0432\u0438\u0434\u0435\u043e \u043f\u043e\u0434 \u0442\u0435\u0433\u043e\u043c",
            "profileThumb": "https://p16-amd-va.tiktokcdn.com/obj/musically-maliva-obj/11b2a0651e37a1bc5a5f6b4336ef5b85.jpeg",
            "profileMedium": "https://p16-amd-va.tiktokcdn.com/obj/musically-maliva-obj/11b2a0651e37a1bc5a5f6b4336ef5b85.jpeg",
            "profileLarger": "https://p16-amd-va.tiktokcdn.com/obj/musically-maliva-obj/11b2a0651e37a1bc5a5f6b4336ef5b85.jpeg",
            "coverThumb": "",
            "coverMedium": "",
            "coverLarger": "",
            "isCommerce": false
        },
        {
            "id": "5303657",
            "title": "\u043b\u0435\u0442\u043e",
            "desc": "\u041d\u0430\u043a\u043e\u043d\u0435\u0446-\u0442\u043e \u043b\u0435\u0442\u043e!\ud83d\udc4f\ud83c\udffb",
            "profileThumb": "",
            "profileMedium": "",
            "profileLarger": "",
            "coverThumb": "",
            "coverMedium": "",
            "coverLarger": "",
            "isCommerce": false
        },
        {
            "id": "1006119",
            "title": "tdm",
            "desc": "",
            "profileThumb": "",
            "profileMedium": "",
            "profileLarger": "",
            "coverThumb": "",
            "coverMedium": "",
            "coverLarger": "",
            "isCommerce": false
        },
        {
            "id": "451042",
            "title": "ukraine",
            "desc": "",
            "profileThumb": "",
            "profileMedium": "",
            "profileLarger": "",
            "coverThumb": "",
            "coverMedium": "",
            "coverLarger": "",
            "isCommerce": false
        },
        {
            "id": "539762",
            "title": "n1",
            "desc": "",
            "profileThumb": "",
            "profileMedium": "",
            "profileLarger": "",
            "coverThumb": "",
            "coverMedium": "",
            "coverLarger": "",
            "isCommerce": false
        },
        {
            "id": "1595387971382277",
            "title": "\u0432\u0440\u0435\u043a",
            "desc": "",
            "profileThumb": "",
            "profileMedium": "",
            "profileLarger": "",
            "coverThumb": "",
            "coverMedium": "",
            "coverLarger": "",
            "isCommerce": false
        },
        {
            "id": "49711363",
            "title": "\u0440\u0435\u043a\u043e\u043c\u0435\u043d\u0434\u0430\u0446\u0438\u0438",
            "desc": "",
            "profileThumb": "",
            "profileMedium": "",
            "profileLarger": "",
            "coverThumb": "",
            "coverMedium": "",
            "coverLarger": "",
            "isCommerce": false
        }
    ],
    "stats": {
        "diggCount": 15,
        "shareCount": 0,
        "commentCount": 3,
        "playCount": 240
    },
    "duetInfo": {
        "duetFromId": "0"
    },
    "originalItem": false,
    "officalItem": false,
    "textExtra": [
        {
            "awemeId": "",
            "start": 11,
            "end": 19,
            "hashtagName": "bye2020",
            "hashtagId": "1640302203126790",
            "type": 1,
            "userId": "",
            "isCommerce": false,
            "userUniqueId": "",
            "secUid": "",
            "subType": 0
        },
        {
            "awemeId": "",
            "start": 20,
            "end": 28,
            "hashtagName": "ukraine",
            "hashtagId": "451042",
            "type": 1,
            "userId": "",
            "isCommerce": false,
            "userUniqueId": "",
            "secUid": "",
            "subType": 0
        },
        {
            "awemeId": "",
            "start": 29,
            "end": 38,
            "hashtagName": "followme",
            "hashtagId": "6856",
            "type": 1,
            "userId": "",
            "isCommerce": false,
            "userUniqueId": "",
            "secUid": "",
            "subType": 0
        },
        {
            "awemeId": "",
            "start": 39,
            "end": 47,
            "hashtagName": "n1kosup",
            "hashtagId": "1650546899645445",
            "type": 1,
            "userId": "",
            "isCommerce": false,
            "userUniqueId": "",
            "secUid": "",
            "subType": 0
        },
        {
            "awemeId": "",
            "start": 48,
            "end": 59,
            "hashtagName": "popularpic",
            "hashtagId": "552988",
            "type": 1,
            "userId": "",
            "isCommerce": false,
            "userUniqueId": "",
            "secUid": "",
            "subType": 0
        },
        {
            "awemeId": "",
            "start": 60,
            "end": 67,
            "hashtagName": "\u0430\u043d\u0434\u0440\u0435\u0439",
            "hashtagId": "5981203",
            "type": 1,
            "userId": "",
            "isCommerce": false,
            "userUniqueId": "",
            "secUid": "",
            "subType": 0
        },
        {
            "awemeId": "",
            "start": 68,
            "end": 74,
            "hashtagName": "\u0432\u0435\u0441\u043d\u0430",
            "hashtagId": "5681299",
            "type": 1,
            "userId": "",
            "isCommerce": false,
            "userUniqueId": "",
            "secUid": "",
            "subType": 0
        },
        {
            "awemeId": "",
            "start": 75,
            "end": 80,
            "hashtagName": "\u043b\u0435\u0442\u043e",
            "hashtagId": "5303657",
            "type": 1,
            "userId": "",
            "isCommerce": false,
            "userUniqueId": "",
            "secUid": "",
            "subType": 0
        },
        {
            "awemeId": "",
            "start": 81,
            "end": 85,
            "hashtagName": "tdm",
            "hashtagId": "1006119",
            "type": 1,
            "userId": "",
            "isCommerce": false,
            "userUniqueId": "",
            "secUid": "",
            "subType": 0
        },
        {
            "awemeId": "",
            "start": 86,
            "end": 94,
            "hashtagName": "ukraine",
            "hashtagId": "451042",
            "type": 1,
            "userId": "",
            "isCommerce": false,
            "userUniqueId": "",
            "secUid": "",
            "subType": 0
        },
        {
            "awemeId": "",
            "start": 95,
            "end": 98,
            "hashtagName": "n1",
            "hashtagId": "539762",
            "type": 1,
            "userId": "",
            "isCommerce": false,
            "userUniqueId": "",
            "secUid": "",
            "subType": 0
        },
        {
            "awemeId": "",
            "start": 99,
            "end": 104,
            "hashtagName": "\u0432\u0440\u0435\u043a",
            "hashtagId": "1595387971382277",
            "type": 1,
            "userId": "",
            "isCommerce": false,
            "userUniqueId": "",
            "secUid": "",
            "subType": 0
        },
        {
            "awemeId": "",
            "start": 105,
            "end": 118,
            "hashtagName": "\u0440\u0435\u043a\u043e\u043c\u0435\u043d\u0434\u0430\u0446\u0438\u0438",
            "hashtagId": "49711363",
            "type": 1,
            "userId": "",
            "isCommerce": false,
            "userUniqueId": "",
            "secUid": "",
            "subType": 0
        }
    ],
    "secret": false,
    "forFriend": false,
    "digged": false,
    "itemCommentStatus": 0,
    "showNotPass": false,
    "vl1": false,
    "itemMute": false,
    "authorStats": {
        "followingCount": 1129,
        "followerCount": 143,
        "heartCount": 954,
        "videoCount": 29,
        "diggCount": 288,
        "heart": 954
    },
    "privateItem": false,
    "duetEnabled": true,
    "stitchEnabled": false,
    "shareEnabled": true,
    "isAd": false
}