{
    "user": {
        "id": "6995246240552797189",
        "shortId": "",
        "uniqueId": "british_military564",
        "nickname": "Military",
        "avatarLarger": "https://p16-sign-va.tiktokcdn.com/tos-maliva-avt-0068/17902c12ba5cd0a37882d47ffaba3a23~c5_1080x1080.jpeg?x-expires=1651010400&x-signature=eaGaP8ZXD08zIVzfGWmV3045ZK0%3D",
        "avatarMedium": "https://p77-sign-va.tiktokcdn.com/tos-maliva-avt-0068/17902c12ba5cd0a37882d47ffaba3a23~c5_720x720.jpeg?x-expires=1651010400&x-signature=jjT1ou37QKgegV25uY06FHohHxo%3D",
        "avatarThumb": "https://p16-sign-va.tiktokcdn.com/tos-maliva-avt-0068/17902c12ba5cd0a37882d47ffaba3a23~c5_100x100.jpeg?x-expires=1651010400&x-signature=ZeUQs9%2Bl298Z%2FyBiS5foR9PlG%2F8%3D",
        "signature": "I love the Military let\u2019s get to 30k",
        "verified": false,
        "secUid": "MS4wLjABAAAABbADtYh-pFd0mHnN9Oe10Qcxda6-4JWTXruX3DB4048Vy24dBNHVphlWy-oEqSbm",
        "ftc": false,
        "relation": 0,
        "openFavorite": false,
        "commentSetting": 0,
        "duetSetting": 0,
        "stitchSetting": 0,
        "privateAccount": false,
        "secret": false,
        "isADVirtual": false,
        "roomId": ""
    },
    "stats": {
        "followerCount": 25900,
        "followingCount": 27,
        "heart": 786300,
        "heartCount": 786300,
        "videoCount": 30,
        "diggCount": 0
    },
    "itemList": []
}