{
    "user": {
        "id": "6671660363836588037",
        "shortId": "",
        "uniqueId": "kalinichenko.k",
        "nickname": "\u0415\u043a\u0430\u0442\u0435\u0440\u0438\u043d\u0430 \u041a\u0430\u043b\u0438\u043d\u0438\u0447\u0435\u043d\u043a",
        "avatarLarger": "https://p16-sign-va.tiktokcdn.com/tos-maliva-avt-0068/be8c872d56ae940485346a845645dddb~c5_1080x1080.jpeg?x-expires=1651010400&x-signature=4z%2BOgqnON3zwtZpiPYGChLT71Ak%3D",
        "avatarMedium": "https://p16-sign-va.tiktokcdn.com/tos-maliva-avt-0068/be8c872d56ae940485346a845645dddb~c5_720x720.jpeg?x-expires=1651010400&x-signature=CCk%2FEpq%2BYnl0VJOT9rHAd69MSJ4%3D",
        "avatarThumb": "https://p16-sign-va.tiktokcdn.com/tos-maliva-avt-0068/be8c872d56ae940485346a845645dddb~c5_100x100.jpeg?x-expires=1651010400&x-signature=wY%2F%2FpKy2OtUv3vwfSr6CzymF1O4%3D",
        "signature": "",
        "verified": false,
        "secUid": "MS4wLjABAAAAJSdm13v9aeL4Esv_mcWWfk22iZ4WmpjWXU_-ze62oTfNNS7Dz8TOl6LVh-mPVbNO",
        "ftc": false,
        "relation": 0,
        "openFavorite": false,
        "commentSetting": 0,
        "duetSetting": 0,
        "stitchSetting": 0,
        "privateAccount": false,
        "secret": false,
        "isADVirtual": false,
        "roomId": ""
    },
    "stats": {
        "followerCount": 25100,
        "followingCount": 450,
        "heart": 262600,
        "heartCount": 262600,
        "videoCount": 1287,
        "diggCount": 0
    },
    "itemList": []
}