{
    "id": "7079709284140911877",
    "desc": "\u042f\u043a\u0449\u043e \u0440\u0435\u043a,\u043a\u0440\u0438\u0447\u0438!\ud83d\ude02\u2764\ufe0f\ud83c\uddfa\ud83c\udde6#\u0437\u0435\u043b\u0435\u043d\u0441\u043a\u0438\u0439 #\u0417\u0435\u043b\u0435\u043d\u0441\u044c\u043a\u0438\u0439\u043a\u0440\u0430\u0448 #\u0417\u0421\u0423 #\u043d\u0430\u0439\u043a\u0440\u0430\u0449\u0456 #\u0417\u0421\u0423 #\u0417\u0421\u0423 #\u0443\u043a\u0440\u0430\u0457\u043d\u0430\ud83c\uddfa\ud83c\udde6",
    "createTime": 1648373271,
    "video": {
        "id": "7079709284140911877",
        "height": 1216,
        "width": 576,
        "duration": 23,
        "ratio": "720p",
        "cover": "https://p16-sign-va.tiktokcdn.com/obj/tos-maliva-p-0068/cfe9aeb4c1ad441eb70c2de2d7af904d?x-expires=1648450800&x-signature=wmuS379nGdrkPVnfToayxnWChhM%3D",
        "originCover": "https://p16-sign-va.tiktokcdn.com/obj/tos-maliva-p-0068/89cbfadf13fa4dc4954b2c9860462579_1648373272?x-expires=1648450800&x-signature=E2gDRbz%2Fyi7pxx3r9a1mWB%2FrRKk%3D",
        "dynamicCover": "https://p16-sign-va.tiktokcdn.com/obj/tos-maliva-p-0068/7b420434a4d94788a0564232b21fc78c_1648373272?x-expires=1648450800&x-signature=u2EY20ax6Yt8CU9scGN2pniMD0U%3D",
        "playAddr": "https://v16m-webapp.tiktokcdn-us.com/12bf751ff675ca19cee03c2b73367f35/62415e80/video/tos/useast2a/tos-useast2a-ve-0068c001/99d25329b98b4d28832a9f0ffe0ddb44/?a=1988&br=2990&bt=1495&cd=0%7C0%7C1%7C0&ch=0&cr=0&cs=0&cv=1&dr=0&ds=3&er=&ft=XY53A3E7nz7ThvbagDXq&l=20220328010617010113006011250C5C61&lr=tiktok_m&mime_type=video_mp4&net=0&pl=0&qs=0&rc=am95aDQ6Zmo1PDMzNzczM0ApOmloOTRkOjw6NzVnMzczZ2dzYDJzcjRvby1gLS1kMTZzc2BhMDBjX15fMTE1MzNeNDQ6Yw%3D%3D&vl=&vr=",
        "downloadAddr": "https://v16m-webapp.tiktokcdn-us.com/12bf751ff675ca19cee03c2b73367f35/62415e80/video/tos/useast2a/tos-useast2a-ve-0068c001/99d25329b98b4d28832a9f0ffe0ddb44/?a=1988&br=2990&bt=1495&cd=0%7C0%7C1%7C0&ch=0&cr=0&cs=0&cv=1&dr=0&ds=3&er=&ft=XY53A3E7nz7ThvbagDXq&l=20220328010617010113006011250C5C61&lr=tiktok_m&mime_type=video_mp4&net=0&pl=0&qs=0&rc=am95aDQ6Zmo1PDMzNzczM0ApOmloOTRkOjw6NzVnMzczZ2dzYDJzcjRvby1gLS1kMTZzc2BhMDBjX15fMTE1MzNeNDQ6Yw%3D%3D&vl=&vr=",
        "shareCover": [
            "",
            "https://p16-sign-va.tiktokcdn.com/tos-maliva-p-0068/89cbfadf13fa4dc4954b2c9860462579_1648373272~tplv-tiktok-play.jpeg?x-expires=1649034000&x-signature=J4j2FxPgyEEKV%2BLouY51WzI6CXM%3D",
            "https://p16-sign-va.tiktokcdn.com/tos-maliva-p-0068/89cbfadf13fa4dc4954b2c9860462579_1648373272~tplv-tiktokx-share-play.jpeg?x-expires=1649034000&x-signature=vVZa6xArdqZEDQUcxvaN6Pc%2F6fY%3D"
        ],
        "reflowCover": "https://p16-sign-va.tiktokcdn.com/obj/tos-maliva-p-0068/cfe9aeb4c1ad441eb70c2de2d7af904d?x-expires=1648450800&x-signature=wmuS379nGdrkPVnfToayxnWChhM%3D",
        "bitrate": 1531567,
        "encodedType": "normal",
        "format": "mp4",
        "videoQuality": "normal",
        "encodeUserTag": ""
    },
    "author": {
        "id": "7079472968355382277",
        "uniqueId": "ukraine_the_best26",
        "nickname": "\u041c\u043e\u0436\u043d\u0430 \u043f\u0456\u0434\u043f\u0438\u0441\u043a\u0443 \u0432\u0456\u0434 \u0443\u043a\u0440\u0430\u0457\u043d\u0446\u044f?\u2764\ufe0f",
        "avatarThumb": "https://p16-sign-va.tiktokcdn.com/tos-maliva-avt-0068/1440c20fe66518ad8752081ab87f19b1~c5_100x100.jpeg?x-expires=1648515600&x-signature=2zw6e2XB0laLDl8mJHTkd9k6P%2B8%3D",
        "avatarMedium": "https://p16-sign-va.tiktokcdn.com/tos-maliva-avt-0068/1440c20fe66518ad8752081ab87f19b1~c5_720x720.jpeg?x-expires=1648515600&x-signature=Af8iP7A05A%2FpnK9aLrjTmAtxgao%3D",
        "avatarLarger": "https://p16-sign-va.tiktokcdn.com/tos-maliva-avt-0068/1440c20fe66518ad8752081ab87f19b1~c5_1080x1080.jpeg?x-expires=1648515600&x-signature=agnCxD7i4OqVHORNxNRV9TQ3tAg%3D",
        "signature": "\ud83d\ude0d\u0414\u041e\u0411\u0420\u041e\u0413\u041e \u0412\u0415\u0427\u041e\u0420\u0410, \u041c\u0418 \u0417 \u0423\u041a\u0420\u0410\u0407\u041d\u0418\u270a\ud83c\uddfa\ud83c\udde6",
        "verified": false,
        "secUid": "MS4wLjABAAAA9a9NPg3YzdF9SDCqZ63dYuiZbTSVWSN70vmi-zZ1D8oltlJh2YeR-gIVnVEldS_7",
        "secret": false,
        "ftc": false,
        "relation": 0,
        "openFavorite": false,
        "commentSetting": 0,
        "duetSetting": 0,
        "stitchSetting": 0,
        "privateAccount": false
    },
    "music": {
        "id": "6991356035818720006",
        "title": "\u043e\u0440\u0438\u0433\u0456\u043d\u0430\u043b\u044c\u043d\u0438\u0439 \u0437\u0432\u0443\u043a",
        "playUrl": "https://sf16-ies-music-va.tiktokcdn.com/obj/musically-maliva-obj/6991356187665337093.mp3",
        "coverThumb": "https://p16-sign-va.tiktokcdn.com/tos-maliva-avt-0068/979f23f998292c213c17d63e3358172f~c5_100x100.jpeg?x-expires=1648515600&x-signature=5zStQ8JJQAOSVSJUKjMXckZfVmI%3D",
        "coverMedium": "https://p16-sign-va.tiktokcdn.com/tos-maliva-avt-0068/979f23f998292c213c17d63e3358172f~c5_720x720.jpeg?x-expires=1648515600&x-signature=fhH7m%2FRipSd95rdaHa11C0D4V7Y%3D",
        "coverLarge": "https://p16-sign-va.tiktokcdn.com/tos-maliva-avt-0068/979f23f998292c213c17d63e3358172f~c5_1080x1080.jpeg?x-expires=1648515600&x-signature=UdTeZGgqZx2L%2BHPVKlpEU7nTcbY%3D",
        "authorName": "\ud83c\uddfa\ud83c\udde6\ud83c\uddfa\ud83c\udde6\ud83c\uddfa\ud83c\udde6\ud83c\udfb6",
        "original": true,
        "duration": 54,
        "album": ""
    },
    "challenges": [
        {
            "id": "83095258",
            "title": "\u0437\u0435\u043b\u0435\u043d\u0441\u043a\u0438\u0439",
            "desc": "",
            "profileThumb": "",
            "profileMedium": "",
            "profileLarger": "",
            "coverThumb": "",
            "coverMedium": "",
            "coverLarger": "",
            "isCommerce": false
        },
        {
            "id": "7068698238546771974",
            "title": "\u0437\u0435\u043b\u0435\u043d\u0441\u044c\u043a\u0438\u0439\u043a\u0440\u0430\u0448",
            "desc": "",
            "profileThumb": "",
            "profileMedium": "",
            "profileLarger": "",
            "coverThumb": "",
            "coverMedium": "",
            "coverLarger": "",
            "isCommerce": false
        },
        {
            "id": "1597357966683142",
            "title": "\u0437\u0441\u0443",
            "desc": "",
            "profileThumb": "",
            "profileMedium": "",
            "profileLarger": "",
            "coverThumb": "",
            "coverMedium": "",
            "coverLarger": "",
            "isCommerce": false
        },
        {
            "id": "20792181",
            "title": "\u043d\u0430\u0439\u043a\u0440\u0430\u0449\u0456",
            "desc": "",
            "profileThumb": "",
            "profileMedium": "",
            "profileLarger": "",
            "coverThumb": "",
            "coverMedium": "",
            "coverLarger": "",
            "isCommerce": false
        },
        {
            "id": "1597357966683142",
            "title": "\u0437\u0441\u0443",
            "desc": "",
            "profileThumb": "",
            "profileMedium": "",
            "profileLarger": "",
            "coverThumb": "",
            "coverMedium": "",
            "coverLarger": "",
            "isCommerce": false
        },
        {
            "id": "1597357966683142",
            "title": "\u0437\u0441\u0443",
            "desc": "",
            "profileThumb": "",
            "profileMedium": "",
            "profileLarger": "",
            "coverThumb": "",
            "coverMedium": "",
            "coverLarger": "",
            "isCommerce": false
        },
        {
            "id": "1618292853536773",
            "title": "\u0443\u043a\u0440\u0430\u0457\u043d\u0430\ud83c\uddfa\ud83c\udde6",
            "desc": "",
            "profileThumb": "",
            "profileMedium": "",
            "profileLarger": "",
            "coverThumb": "",
            "coverMedium": "",
            "coverLarger": "",
            "isCommerce": false
        }
    ],
    "stats": {
        "diggCount": 173,
        "shareCount": 2,
        "commentCount": 5,
        "playCount": 2545
    },
    "duetInfo": {
        "duetFromId": "0"
    },
    "originalItem": false,
    "officalItem": false,
    "textExtra": [
        {
            "awemeId": "",
            "start": 23,
            "end": 33,
            "hashtagName": "\u0437\u0435\u043b\u0435\u043d\u0441\u043a\u0438\u0439",
            "hashtagId": "83095258",
            "type": 1,
            "userId": "",
            "isCommerce": false,
            "userUniqueId": "",
            "secUid": "",
            "subType": 0
        },
        {
            "awemeId": "",
            "start": 34,
            "end": 49,
            "hashtagName": "\u0437\u0435\u043b\u0435\u043d\u0441\u044c\u043a\u0438\u0439\u043a\u0440\u0430\u0448",
            "hashtagId": "7068698238546771974",
            "type": 1,
            "userId": "",
            "isCommerce": false,
            "userUniqueId": "",
            "secUid": "",
            "subType": 0
        },
        {
            "awemeId": "",
            "start": 50,
            "end": 54,
            "hashtagName": "\u0437\u0441\u0443",
            "hashtagId": "1597357966683142",
            "type": 1,
            "userId": "",
            "isCommerce": false,
            "userUniqueId": "",
            "secUid": "",
            "subType": 0
        },
        {
            "awemeId": "",
            "start": 55,
            "end": 64,
            "hashtagName": "\u043d\u0430\u0439\u043a\u0440\u0430\u0449\u0456",
            "hashtagId": "20792181",
            "type": 1,
            "userId": "",
            "isCommerce": false,
            "userUniqueId": "",
            "secUid": "",
            "subType": 0
        },
        {
            "awemeId": "",
            "start": 65,
            "end": 69,
            "hashtagName": "\u0437\u0441\u0443",
            "hashtagId": "1597357966683142",
            "type": 1,
            "userId": "",
            "isCommerce": false,
            "userUniqueId": "",
            "secUid": "",
            "subType": 0
        },
        {
            "awemeId": "",
            "start": 70,
            "end": 74,
            "hashtagName": "\u0437\u0441\u0443",
            "hashtagId": "1597357966683142",
            "type": 1,
            "userId": "",
            "isCommerce": false,
            "userUniqueId": "",
            "secUid": "",
            "subType": 0
        },
        {
            "awemeId": "",
            "start": 75,
            "end": 87,
            "hashtagName": "\u0443\u043a\u0440\u0430\u0457\u043d\u0430\ud83c\uddfa\ud83c\udde6",
            "hashtagId": "1618292853536773",
            "type": 1,
            "userId": "",
            "isCommerce": false,
            "userUniqueId": "",
            "secUid": "",
            "subType": 0
        }
    ],
    "secret": false,
    "forFriend": false,
    "digged": false,
    "itemCommentStatus": 0,
    "showNotPass": false,
    "vl1": false,
    "itemMute": false,
    "authorStats": {
        "followingCount": 5,
        "followerCount": 53,
        "heartCount": 574,
        "videoCount": 8,
        "diggCount": 27,
        "heart": 574
    },
    "privateItem": false,
    "duetEnabled": true,
    "stitchEnabled": true,
    "shareEnabled": true,
    "isAd": false
}