{
    "user": {
        "id": "6783095232730874885",
        "shortId": "",
        "uniqueId": "ozn1453_",
        "nickname": "Die\u00c4raT\u00fcrkei",
        "avatarLarger": "https://p77-sign-va.tiktokcdn.com/tos-maliva-avt-0068/6da90b14c772b91bf20d4fe1431b5e31~c5_1080x1080.jpeg?x-expires=1646773200&x-signature=F9KAekuffsBUA%2BdvIfBMEUIkm7w%3D",
        "avatarMedium": "https://p77-sign-va.tiktokcdn.com/tos-maliva-avt-0068/6da90b14c772b91bf20d4fe1431b5e31~c5_720x720.jpeg?x-expires=1646773200&x-signature=L%2FENRmvXmh%2BG9a%2Fnm%2BKxKsm5Fg0%3D",
        "avatarThumb": "https://p77-sign-va.tiktokcdn.com/tos-maliva-avt-0068/6da90b14c772b91bf20d4fe1431b5e31~c5_100x100.jpeg?x-expires=1646773200&x-signature=QnHBsaL22f5xVoxjA0PL6VJ%2Fzm8%3D",
        "signature": "AKP | Partei f\u00fcr Gerechtigkeit und Aufschwung. \n\ud83c\uddf9\ud83c\uddf7 \ud83c\udde6\ud83c\uddff\nALLAHU AKBAR! \ud83d\udd4b",
        "createTime": 1611512226,
        "verified": false,
        "secUid": "MS4wLjABAAAATDgTQFQ5MoOCac56kCHQz18bQx0Z1mbJ5D-clzmYujUGXykacj9FeGxluHdIa7A9",
        "ftc": false,
        "relation": 0,
        "openFavorite": false,
        "commentSetting": 0,
        "duetSetting": 0,
        "stitchSetting": 0,
        "privateAccount": false,
        "secret": false,
        "isADVirtual": false,
        "roomId": ""
    },
    "stats": {
        "followerCount": 23000,
        "followingCount": 1,
        "heart": 339700,
        "heartCount": 339700,
        "videoCount": 122,
        "diggCount": 0
    },
    "itemList": []
}