{
    "user": {
        "id": "7042748930337801217",
        "shortId": "",
        "uniqueId": "eurovision_n",
        "nickname": "\u0415\u0432\u0440\u043e\u0432\u0438\u0434\u0435\u043d\u0438\u0435",
        "avatarLarger": "https://p58-sign-sg.tiktokcdn.com/aweme/1080x1080/tos-alisg-avt-0068/93bb2dfdf4ab78f407aeee06529eb367.jpeg?x-expires=1647050400&x-signature=ZG5tTEFkfBd5Nw0KdCuHGeLDcGQ%3D",
        "avatarMedium": "https://p58-sign-sg.tiktokcdn.com/aweme/720x720/tos-alisg-avt-0068/93bb2dfdf4ab78f407aeee06529eb367.jpeg?x-expires=1647050400&x-signature=I3HDkIKkRjl6apE7cLaRBjNKPA4%3D",
        "avatarThumb": "https://p16-sign-sg.tiktokcdn.com/aweme/100x100/tos-alisg-avt-0068/93bb2dfdf4ab78f407aeee06529eb367.jpeg?x-expires=1647050400&x-signature=d6n0tCQ8B0l8wgp6t33ARpZAsIs%3D",
        "signature": "\u0412\u0440\u0435\u043c\u0435\u043d\u043d\u043e \u0432\u0438\u0434\u0435\u043e \u043d\u0435 \u0431\u0443\u0434\u0435\u0442\n\u0417\u0434\u0435\u0441\u044c \u0442\u043e\u043b\u044c\u043a\u043e \u0415\u0432\u0440\u043e\u0432\u0438\u0434\u0435\u043d\u0438\u0435\ud83c\udf99",
        "createTime": 1639768397,
        "verified": false,
        "secUid": "MS4wLjABAAAA3-q5_6rrN25RUnEyOFNBFwkVTd-MDvfhwX6yxbS8cBWZlFf7DEZNOJF9BDAmO3Yh",
        "ftc": false,
        "relation": 0,
        "openFavorite": false,
        "commentSetting": 0,
        "commerceUserInfo": {
            "commerceUser": true,
            "downLoadLink": {},
            "category": "Others",
            "categoryButton": false
        },
        "duetSetting": 0,
        "stitchSetting": 0,
        "privateAccount": false,
        "secret": false,
        "isADVirtual": false,
        "roomId": ""
    },
    "stats": {
        "followerCount": 18500,
        "followingCount": 13,
        "heart": 1200000,
        "heartCount": 1200000,
        "videoCount": 28,
        "diggCount": 0
    },
    "itemList": []
}